<?xml version="1.0" encoding="UTF-8"?><element type_str="object" name_str="root"><element type_str="string" name_str="title"><![CDATA[functionalities]]></element><element type_str="string" name_str="deeplink"><![CDATA[flash.cms/what.can.silex.do/functionalities]]></element><element type_str="string" name_str="pubDate"><![CDATA[Mon Oct 18 17:08:42 GMT+0200 2010]]></element><element type_str="string" name_str="urlBase"><![CDATA[http://localhost:80/trunk_silex/apps/themes/website/silex/]]></element><element type_str="object" name_str="content"><element type_str="object" name_str="0"><element type_str="string" name_str="context"><![CDATA[*]]></element><element type_str="string" name_str="text"><![CDATA[Designers and developers]]></element><element type_str="string" name_str="htmlEquivalent"><![CDATA[<p><TEXTFORMAT LEADING="2"><P ALIGN="LEFT"><FONT FACE="_sans" SIZE="30" COLOR="#FFFFFF" LETTERSPACING="0" KERNING="0">Designers and developers</FONT></P></TEXTFORMAT></p>]]></element></element><element type_str="object" name_str="1"><element type_str="string" name_str="context"><![CDATA[*]]></element><element type_str="string" name_str="text"><![CDATA[ Designers, in order to build maintainable, optimized and full featured Flash websites, you only need Silex and whatever software you use to design the background, illustrations, etc. In Silex you can add interactivity and build the structure of your publication. With Flash you will be able to add more complex interactivity and customize components and animation.SILEX users have chosen this tool for :    * its automatic SEO system    * its multilingual contexts management    * its constant evolution    * its documentation and the ever growing designers and developers community    * the SILEX components and themes provided with it    * the Flash look and feel of the produced applications    * its legitimate integration in the CS5 package    * its short learning curveLinks    * get started with the online demo: http://demos.silexlabs.org/silex/    * showcase: http://www.silexlabs.org/the-blog/fr/rate-showcase/     * download themes and components: http://exchange.silexlabs.org/Dynamic sites development]]></element><element type_str="string" name_str="htmlEquivalent"><![CDATA[<p><TEXTFORMAT LEADING="2"><P ALIGN="LEFT"><FONT FACE="_sans" SIZE="16" COLOR="#FFFFFF" LETTERSPACING="0" KERNING="0"> Designers, in order to build maintainable, optimized and full featured Flash websites, you only need Silex and whatever software you use to design the background, illustrations, etc. In Silex you can add interactivity and build the structure of your publication. With Flash you will be able to add more complex interactivity and customize components and animation.</FONT></P></TEXTFORMAT><TEXTFORMAT LEADING="2"><P ALIGN="LEFT"><FONT FACE="_sans" SIZE="16" COLOR="#FFFFFF" LETTERSPACING="0" KERNING="0"></FONT></P></TEXTFORMAT><TEXTFORMAT LEADING="2"><P ALIGN="LEFT"><FONT FACE="_sans" SIZE="16" COLOR="#FFFFFF" LETTERSPACING="0" KERNING="0">SILEX users have chosen this tool for :</FONT></P></TEXTFORMAT><TEXTFORMAT LEADING="2"><P ALIGN="LEFT"><FONT FACE="_sans" SIZE="16" COLOR="#FFFFFF" LETTERSPACING="0" KERNING="0"></FONT></P></TEXTFORMAT><TEXTFORMAT LEADING="2"><P ALIGN="LEFT"><FONT FACE="_sans" SIZE="16" COLOR="#FFFFFF" LETTERSPACING="0" KERNING="0">    * its automatic SEO system</FONT></P></TEXTFORMAT><TEXTFORMAT LEADING="2"><P ALIGN="LEFT"><FONT FACE="_sans" SIZE="16" COLOR="#FFFFFF" LETTERSPACING="0" KERNING="0">    * its multilingual contexts management</FONT></P></TEXTFORMAT><TEXTFORMAT LEADING="2"><P ALIGN="LEFT"><FONT FACE="_sans" SIZE="16" COLOR="#FFFFFF" LETTERSPACING="0" KERNING="0">    * its constant evolution</FONT></P></TEXTFORMAT><TEXTFORMAT LEADING="2"><P ALIGN="LEFT"><FONT FACE="_sans" SIZE="16" COLOR="#FFFFFF" LETTERSPACING="0" KERNING="0">    * its documentation and the ever growing designers and developers community</FONT></P></TEXTFORMAT><TEXTFORMAT LEADING="2"><P ALIGN="LEFT"><FONT FACE="_sans" SIZE="16" COLOR="#FFFFFF" LETTERSPACING="0" KERNING="0">    * the SILEX components and themes provided with it</FONT></P></TEXTFORMAT><TEXTFORMAT LEADING="2"><P ALIGN="LEFT"><FONT FACE="_sans" SIZE="16" COLOR="#FFFFFF" LETTERSPACING="0" KERNING="0">    * the Flash look and feel of the produced applications</FONT></P></TEXTFORMAT><TEXTFORMAT LEADING="2"><P ALIGN="LEFT"><FONT FACE="_sans" SIZE="16" COLOR="#FFFFFF" LETTERSPACING="0" KERNING="0">    * its legitimate integration in the CS5 package</FONT></P></TEXTFORMAT><TEXTFORMAT LEADING="2"><P ALIGN="LEFT"><FONT FACE="_sans" SIZE="16" COLOR="#FFFFFF" LETTERSPACING="0" KERNING="0">    * its short learning curve</FONT></P></TEXTFORMAT><TEXTFORMAT LEADING="2"><P ALIGN="LEFT"><FONT FACE="_sans" SIZE="16" COLOR="#FFFFFF" LETTERSPACING="0" KERNING="0"></FONT></P></TEXTFORMAT><TEXTFORMAT LEADING="2"><P ALIGN="LEFT"><FONT FACE="_sans" SIZE="16" COLOR="#FFFFFF" LETTERSPACING="0" KERNING="0">Links</FONT></P></TEXTFORMAT><TEXTFORMAT LEADING="2"><P ALIGN="LEFT"><FONT FACE="_sans" SIZE="16" COLOR="#FFFFFF" LETTERSPACING="0" KERNING="0"></FONT></P></TEXTFORMAT><TEXTFORMAT LEADING="2"><P ALIGN="LEFT"><FONT FACE="_sans" SIZE="16" COLOR="#FFFFFF" LETTERSPACING="0" KERNING="0">    * get started with the online demo: http://demos.silexlabs.org/silex/</FONT></P></TEXTFORMAT><TEXTFORMAT LEADING="2"><P ALIGN="LEFT"><FONT FACE="_sans" SIZE="16" COLOR="#FFFFFF" LETTERSPACING="0" KERNING="0">    * showcase: http://www.silexlabs.org/the-blog/fr/rate-showcase/ </FONT></P></TEXTFORMAT><TEXTFORMAT LEADING="2"><P ALIGN="LEFT"><FONT FACE="_sans" SIZE="16" COLOR="#FFFFFF" LETTERSPACING="0" KERNING="0">    * download themes and components: http://exchange.silexlabs.org/</FONT></P></TEXTFORMAT><TEXTFORMAT LEADING="2"><P ALIGN="LEFT"><FONT FACE="_sans" SIZE="16" COLOR="#FFFFFF" LETTERSPACING="0" KERNING="0"></FONT></P></TEXTFORMAT><TEXTFORMAT LEADING="2"><P ALIGN="LEFT"><FONT FACE="_sans" SIZE="16" COLOR="#FFFFFF" LETTERSPACING="0" KERNING="0">Dynamic sites development</FONT></P></TEXTFORMAT></p>]]></element></element><element type_str="object" name_str="2"><element type_str="string" name_str="context"><![CDATA[*]]></element><element type_str="string" name_str="htmlEquivalent"><![CDATA[<img name="footer" src="../../../../media/logosilex.jpg">]]></element></element></element></element>